react_native_debugger_client/__init__.py
react_native_debugger_client/client.py
react_native_debugger_client/javascript_executor.py
react_native_debugger_client/js_snippets/__init__.py
react_native_debugger_client/js_snippets/interaction.py
react_native_debugger_client/js_snippets/ui.py
react_native_debugger_client-0.0.1.dev1.dist-info/licenses/LICENSE
tests/__init__.py
tests/test_debugger_client.py
react_native_debugger_client-0.0.1.dev1.dist-info/METADATA
react_native_debugger_client-0.0.1.dev1.dist-info/WHEEL
react_native_debugger_client-0.0.1.dev1.dist-info/top_level.txt
react_native_debugger_client-0.0.1.dev1.dist-info/RECORD
