Metadata-Version: 2.4
Name: react-native-debugger-client
Version: 0.0.1.dev1
Summary: A Python client for interacting with React Native applications via the Hermes debugger
Home-page: https://github.com/erickjtorres/react-native-debugger-client
Author: Erick Torres-Moreno
License: MIT
Project-URL: Homepage, https://github.com/erickjtorres/react-native-debugger-client
Project-URL: Issues, https://github.com/erickjtorres/react-native-debugger-client/issues
Keywords: react-native,hermes,debugger,testing,automation
Classifier: Development Status :: 4 - Beta
Classifier: Intended Audience :: Developers
Classifier: Topic :: Software Development :: Testing
Classifier: Topic :: Software Development :: Debuggers
Classifier: Programming Language :: Python :: 3
Classifier: Programming Language :: Python :: 3.7
Classifier: Programming Language :: Python :: 3.8
Classifier: Programming Language :: Python :: 3.9
Classifier: Programming Language :: Python :: 3.10
Classifier: Programming Language :: Python :: 3.11
Classifier: License :: OSI Approved :: MIT License
Classifier: Operating System :: OS Independent
Requires-Python: >=3.7
License-File: LICENSE
Requires-Dist: requests>=2.28.0
Requires-Dist: websocket-client>=1.3.0
Dynamic: home-page
Dynamic: license-file
Dynamic: requires-python
